oci/__init__.py
oci/utils.py
src/__init__.py
src/auth.py
src/config.py
src/dhuolib.py
src/predict.py
src/services.py
src/setup.py
src/utils.py
src/worker.py
src/oci/__init__.py
src/oci/utils.py
tests/__init__.py
tests/test_dhuolib.py
tests/test_services.py
tests/test_utils.py
dhuolib_tools-0.0.7.dist-info/METADATA
dhuolib_tools-0.0.7.dist-info/WHEEL
dhuolib_tools-0.0.7.dist-info/top_level.txt
dhuolib_tools-0.0.7.dist-info/RECORD
