Metadata-Version: 2.1
Name: dhuolib-tools
Version: 0.0.7
Home-page: https://gitlab.engdb.com.br/dhuo-plat/dhuo-data/data-science/dhuolib
Author: DHuO Data Team
Author-email: diego.salles@engdb.com.br
Platform: any
Requires-Dist: mlflow
Requires-Dist: oci ==2.125.3
Provides-Extra: interactive
Requires-Dist: mypy ==1.5.1 ; extra == 'interactive'
Requires-Dist: flake8 ==6.1.0 ; extra == 'interactive'
Requires-Dist: black ==22.3.0 ; extra == 'interactive'
Requires-Dist: pytest-cov ~=4.0 ; extra == 'interactive'
Requires-Dist: pytest ~=7.0 ; extra == 'interactive'
Requires-Dist: twine ; extra == 'interactive'
Requires-Dist: wheel ; extra == 'interactive'
